messageit/__init__.py
messageit/_message.py
messageit-0.1.0.dist-info/LICENSE
messageit-0.1.0.dist-info/METADATA
messageit-0.1.0.dist-info/WHEEL
messageit-0.1.0.dist-info/top_level.txt
messageit-0.1.0.dist-info/RECORD
