Metadata-Version: 2.1
Name: messageit
Version: 0.1.0
Summary: Message (Command and Event) passing for Python
Home-page: https://github.com/ivangeorgiev/messageit
Author: Ivan Georgiev
Author-email: ivan.georgiev@gmail.com
License: Creative Commons Zero v1.0 Universal
Keywords: message passing,messate bus,commands,events
Classifier: Programming Language :: Python :: 3
Classifier: Operating System :: OS Independent
License-File: LICENSE
